README.md
setup.py
ultratransmission/__init__.py
ultratransmission/bin.py
ultratransmission/ultratransmission.py
ultratransmission.egg-info/PKG-INFO
ultratransmission.egg-info/SOURCES.txt
ultratransmission.egg-info/dependency_links.txt
ultratransmission.egg-info/entry_points.txt
ultratransmission.egg-info/requires.txt
ultratransmission.egg-info/top_level.txt