Metadata-Version: 1.1
Name: ultratransmission
Version: 1.6.4
Summary: Automatically trigger torrents to download through transmission web client
Home-page: https://bitbucket.org/johannestaas/ultratransmission
Author: Johan Nestaas
Author-email: johannestaas@gmail.com
License: GPLv3+
Keywords: pirate bay transmission torrent magnet
Platform: UNKNOWN
Classifier: Development Status :: 4 - Beta
Classifier: License :: OSI Approved :: GNU General Public License v3 or later (GPLv3+)
Classifier: Environment :: Console
Classifier: Environment :: X11 Applications :: Qt
Classifier: Environment :: MacOS X
Classifier: Environment :: Win32 (MS Windows)
Classifier: Operating System :: POSIX
Classifier: Operating System :: MacOS :: MacOS X
Classifier: Operating System :: Microsoft :: Windows
Classifier: Programming Language :: Python
